django_letsencrypt-5.1.0.dist-info/licenses/LICENSE
letsencrypt/__init__.py
letsencrypt/admin.py
letsencrypt/apps.py
letsencrypt/models.py
letsencrypt/tests.py
letsencrypt/urls.py
letsencrypt/views.py
letsencrypt/migrations/0001_squashed_0004_squash_for_mysql_support.py
letsencrypt/migrations/__init__.py
django_letsencrypt-5.1.0.dist-info/METADATA
django_letsencrypt-5.1.0.dist-info/WHEEL
django_letsencrypt-5.1.0.dist-info/top_level.txt
django_letsencrypt-5.1.0.dist-info/RECORD
